openvlm/__init__.py
openvlm-0.0.1.dist-info/LICENSE
openvlm-0.0.1.dist-info/METADATA
openvlm-0.0.1.dist-info/WHEEL
openvlm-0.0.1.dist-info/top_level.txt
openvlm-0.0.1.dist-info/RECORD
